ImgTrimmer/Trimmer.py
ImgTrimmer/__init__.py
ImgTrimmer-0.0.1.dist-info/METADATA
ImgTrimmer-0.0.1.dist-info/WHEEL
ImgTrimmer-0.0.1.dist-info/top_level.txt
ImgTrimmer-0.0.1.dist-info/RECORD
